[
    {
    "id": 2,
    "firstName": "Jason",
    "lastName": "Monroe",
    "favoriteLanguage": "C#",
    "yearStarted": 2008
    },
    {
    "id": 3,
    "firstName": "Bill",
    "lastName": "Gates",
    "favoriteLanguage": "BASIC",
    "yearStarted": 1978
    },
    {
    "id": 8,
    "firstName": "Can",
    "lastName": "Y",
    "favoriteLanguage": "Java",
    "yearStarted": 2003
    },
    {
    "id": 9,
    "firstName": "Dima",
    "lastName": "Orlov",
    "favoriteLanguage": "Python",
    "yearStarted": 2017
    },
    {
    "id": 11,
    "firstName": "sasmita",
    "lastName": "patel",
    "favoriteLanguage": "english",
    "yearStarted": 1955
    },
    {
    "id": 13,
    "firstName": "Sumit",
    "lastName": "Yadav",
    "favoriteLanguage": "Java",
    "yearStarted": 2010
    },
    {
    "id": 14,
    "firstName": "Johnny",
    "lastName": "B",
    "favoriteLanguage": "C#",
    "yearStarted": 2000
    },
    {
    "id": 16,
    "firstName": "Venkat",
    "lastName": "B",
    "favoriteLanguage": "Eng",
    "yearStarted": 2000
    },
    {
    "id": 17,
    "firstName": "Ganesh",
    "lastName": "Subramony",
    "favoriteLanguage": "Java",
    "yearStarted": 2016
    },
    {
    "id": 18,
    "firstName": "Kavi",
    "lastName": "Bala",
    "favoriteLanguage": "JS",
    "yearStarted": 2010
    },
    {
    "id": 19,
    "firstName": "Rajeev",
    "lastName": "Munu",
    "favoriteLanguage": "Informix",
    "yearStarted": 2017
    },
    {
    "id": 29,
    "firstName": "Aidan",
    "lastName": "Geaghan",
    "favoriteLanguage": "Java",
    "yearStarted": 2013
    },
    {
    "id": 30,
    "firstName": "Sang",
    "lastName": "Visu",
    "favoriteLanguage": "Java",
    "yearStarted": 2004
    },
    {
    "id": 35,
    "firstName": "Suneela Bio",
    "lastName": "Borra Bio",
    "favoriteLanguage": "java",
    "yearStarted": 2008
    },
    {
    "id": 134,
    "firstName": "David",
    "lastName": "Brown",
    "favoriteLanguage": "Python",
    "yearStarted": 2017
    },
    {
    "id": 42,
    "firstName": "Elizabeth",
    "lastName": "Swaminathan",
    "favoriteLanguage": "JAVA",
    "yearStarted": 2015
    },
    {
    "id": 74,
    "firstName": "Aiyaz",
    "lastName": "Mak",
    "favoriteLanguage": "Angular",
    "yearStarted": 2019
    },
    {
    "id": 45,
    "firstName": "harshika",
    "lastName": "ponagoti",
    "favoriteLanguage": "java",
    "yearStarted": 2015
    },
    {
    "id": 46,
    "firstName": "Dani",
    "lastName": "Ramesh",
    "favoriteLanguage": "C",
    "yearStarted": 2018
    },
    {
    "id": 48,
    "firstName": "Kevin",
    "lastName": "Rocks",
    "favoriteLanguage": "Java",
    "yearStarted": 2019
    },
    {
    "id": 49,
    "firstName": "Jose",
    "lastName": "Velasco",
    "favoriteLanguage": "java",
    "yearStarted": 2012
    },
    {
    "id": 133,
    "firstName": "Jack",
    "lastName": "Sparrow",
    "favoriteLanguage": "Parley",
    "yearStarted": 2010
    },
    {
    "id": 51,
    "firstName": "Marta",
    "lastName": "Pikhur",
    "favoriteLanguage": "Java",
    "yearStarted": 2013
    },
    {
    "id": 79,
    "firstName": "NARUTO",
    "lastName": "UZAMAKI",
    "favoriteLanguage": "JAPANESE",
    "yearStarted": 1997
    },
    {
    "id": 131,
    "firstName": "David",
    "lastName": "Brown",
    "favoriteLanguage": "Python",
    "yearStarted": 2017
    },
    {
    "id": 132,
    "firstName": "Meethu",
    "lastName": "v",
    "favoriteLanguage": "j",
    "yearStarted": 2019
    },
    {
    "id": 129,
    "firstName": "Meethu",
    "lastName": "vr",
    "favoriteLanguage": "JAVA",
    "yearStarted": 2019
    },
    {
    "id": 52,
    "firstName": "Suresh",
    "lastName": "Nalli",
    "favoriteLanguage": "Java",
    "yearStarted": 2019
    },
    {
    "id": 84,
    "firstName": "Duniel",
    "lastName": "Garcia",
    "favoriteLanguage": "Python/C#",
    "yearStarted": 2017
    },
    {
    "id": 83,
    "firstName": "Sam",
    "lastName": "Moses",
    "favoriteLanguage": "Dothraki",
    "yearStarted": 2018
    },
    {
    "id": 190,
    "firstName": "postdev",
    "lastName": "R",
    "favoriteLanguage": "C#",
    "yearStarted": 2010
    },
    {
    "id": 188,
    "firstName": "Radhika",
    "lastName": "Kapur",
    "favoriteLanguage": "Java",
    "yearStarted": 2000
    },
    {
    "id": 87,
    "firstName": "Anand",
    "lastName": "Shandilya",
    "favoriteLanguage": "Java",
    "yearStarted": 2002
    },
    {
    "id": 126,
    "firstName": "Abstract",
    "lastName": "Data",
    "favoriteLanguage": "C#",
    "yearStarted": 2010
    },
    {
    "id": 92,
    "firstName": "narendra",
    "lastName": "vuddanti",
    "favoriteLanguage": "java",
    "yearStarted": 2015
    },
    {
    "id": 125,
    "firstName": "Senthil",
    "lastName": "Senthil",
    "favoriteLanguage": "java",
    "yearStarted": 2009
    },
    {
    "id": 96,
    "firstName": "Anand1",
    "lastName": "Shandilya",
    "favoriteLanguage": "Java",
    "yearStarted": 2002
    },
    {
    "id": 102,
    "firstName": "Mahesha",
    "lastName": "Gouli",
    "favoriteLanguage": "Angular",
    "yearStarted": 2019
    },
    {
    "id": 104,
    "firstName": "Sunil",
    "lastName": "Kumar",
    "favoriteLanguage": "Java",
    "yearStarted": 1000
    },
    {
    "id": 106,
    "firstName": "Ahmed",
    "lastName": "ElMallah",
    "favoriteLanguage": "Java",
    "yearStarted": 2019
    },
    {
    "id": 107,
    "firstName": "Raja",
    "lastName": "Balraj",
    "favoriteLanguage": "Angular",
    "yearStarted": 2018
    },
    {
    "id": 108,
    "firstName": "Vasu",
    "lastName": "Sunil",
    "favoriteLanguage": "Java",
    "yearStarted": 100
    },
    {
    "id": 109,
    "firstName": "Ishan",
    "lastName": "Samantaray",
    "favoriteLanguage": "Java",
    "yearStarted": 2007
    },
    {
    "id": 110,
    "firstName": "Senthil",
    "lastName": "Ayyaswamy",
    "favoriteLanguage": "Java",
    "yearStarted": 2005
    },
    {
    "id": 112,
    "firstName": "Suman",
    "lastName": "Karmakar",
    "favoriteLanguage": "Java",
    "yearStarted": 2007
    },
    {
    "id": 120,
    "firstName": "bhanu",
    "lastName": "gamidi",
    "favoriteLanguage": "Java",
    "yearStarted": 2007
    },
    {
    "id": 115,
    "firstName": "Saravanakumar",
    "lastName": "Ganesh",
    "favoriteLanguage": "Python",
    "yearStarted": 2011
    },
    {
    "id": 117,
    "firstName": "Andy",
    "lastName": "Roberts",
    "favoriteLanguage": "English",
    "yearStarted": 1999
    },
    {
    "id": 136,
    "firstName": "Jack",
    "lastName": "Sparrow",
    "favoriteLanguage": "parley",
    "yearStarted": 2010
    },
    {
    "id": 138,
    "firstName": "Jack",
    "lastName": "Sparrow",
    "favoriteLanguage": "parley",
    "yearStarted": 2011
    },
    {
    "id": 139,
    "firstName": "Ferose",
    "lastName": "Khan",
    "favoriteLanguage": "C",
    "yearStarted": 2010
    },
    {
    "id": 142,
    "firstName": "Jack",
    "lastName": "Sparrow",
    "favoriteLanguage": "parley",
    "yearStarted": 2012
    },
    {
    "id": 148,
    "firstName": "subhadra",
    "lastName": "poddar",
    "favoriteLanguage": "java",
    "yearStarted": 1985
    },
    {
    "id": 150,
    "firstName": "Vishnu",
    "lastName": "KV",
    "favoriteLanguage": "Java",
    "yearStarted": 2009
    },
    {
    "id": 192,
    "firstName": "Srinu",
    "lastName": "M",
    "favoriteLanguage": "C",
    "yearStarted": 2000
    },
    {
    "id": 193,
    "firstName": "Sriram",
    "lastName": "Srinivasan",
    "favoriteLanguage": "C#",
    "yearStarted": 2007
    },
    {
    "id": 194,
    "firstName": "Mouli",
    "lastName": "Sankar",
    "favoriteLanguage": "c#",
    "yearStarted": 2010
    },
    {
    "id": 195,
    "firstName": "Dinesh",
    "lastName": "Mani",
    "favoriteLanguage": "C#",
    "yearStarted": 2004
    },
    {
    "id": 196,
    "firstName": "Ramesh",
    "lastName": "Pilla",
    "favoriteLanguage": "Java",
    "yearStarted": 2005
    },
    {
    "id": 198,
    "firstName": "Ramesh",
    "lastName": "Balu",
    "favoriteLanguage": "C#",
    "yearStarted": 2010
    },
    {
    "id": 226,
    "firstName": "New 3-23",
    "lastName": "Monroe",
    "favoriteLanguage": "VB",
    "yearStarted": 1980
    },
    {
    "id": 203,
    "firstName": "Mouli Test",
    "lastName": "Test2",
    "favoriteLanguage": "angular",
    "yearStarted": 2019
    },
    {
    "id": 225,
    "firstName": "test 3-18",
    "lastName": "test",
    "favoriteLanguage": "blah",
    "yearStarted": 1980
    },
    {
    "id": 206,
    "firstName": "Caden",
    "lastName": "Ernd",
    "favoriteLanguage": "C++",
    "yearStarted": 2003
    },
    {
    "id": 207,
    "firstName": "Jack",
    "lastName": "Daniels",
    "favoriteLanguage": "C",
    "yearStarted": 1966
    },
    {
    "id": 208,
    "firstName": "Ranky",
    "lastName": "Sundaram",
    "favoriteLanguage": "ASP",
    "yearStarted": 2001
    },
    {
    "id": 209,
    "firstName": "Jamie",
    "lastName": "Ernd",
    "favoriteLanguage": "vb",
    "yearStarted": 2003
    },
    {
    "id": 210,
    "firstName": "TarynXXXXX",
    "lastName": "Ernd",
    "favoriteLanguage": "c++",
    "yearStarted": 1993
    },
    {
    "id": 211,
    "firstName": "Susan",
    "lastName": "De",
    "favoriteLanguage": "C#",
    "yearStarted": 1990
    },
    {
    "id": 212,
    "firstName": "Susan",
    "lastName": "Bio",
    "favoriteLanguage": "C",
    "yearStarted": 1999
    },
    {
    "id": 213,
    "firstName": "Kallol",
    "lastName": "Bhattacharaya",
    "favoriteLanguage": "VB",
    "yearStarted": 2001
    },
    {
    "id": 214,
    "firstName": "Medha",
    "lastName": "Medha",
    "favoriteLanguage": "C#",
    "yearStarted": 2003
    },
    {
    "id": 215,
    "firstName": "Chandu",
    "lastName": "Kandula",
    "favoriteLanguage": "Java",
    "yearStarted": 2007
    },
    {
    "id": 224,
    "firstName": "2020",
    "lastName": "THOMPSON",
    "favoriteLanguage": "refe",
    "yearStarted": 2003
    },
    {
    "id": 217,
    "firstName": "Arnab",
    "lastName": "Chatterjee",
    "favoriteLanguage": "Bengali",
    "yearStarted": 1980
    },
    {
    "id": 223,
    "firstName": "Jason 3-18",
    "lastName": "Monroe",
    "favoriteLanguage": "VB",
    "yearStarted": 1999
    }
    ]